{
  "Mississippi": [
    32.3546679,
    -89.3985283,
    "Mississippi, USA",
    0.75
  ],
  "mississippi": [
    32.3546679,
    -89.3985283,
    "Mississippi, USA",
    0.75
  ],
  "mississippi_usa": [
    32.3546679,
    -89.3985283,
    "Mississippi, USA",
    0.75
  ],
  "pheba_clay_mississippi_usa": [
    33.5847365,
    -88.9495943,
    "Pheba, MS 39755, USA",
    0.75
  ],
  "mississippi_united_states": [
    32.3546679,
    -89.3985283,
    "Mississippi, USA",
    0.75
  ],
  "beat_2_beat_2_sunflower_mississippi_usa": [
    33.4490688,
    -90.6420363,
    "2nd St, Indianola, MS 38751, USA",
    0.75
  ],
  "chicago_cook_illinois_united_states_of_america": [
    41.8781136,
    -87.6297982,
    "Chicago, IL, USA",
    0.75
  ],
  "ruleville_sunflower_mississippi_usa": [
    33.7259478,
    -90.55148059999999,
    "Ruleville, MS 38771, USA",
    0.75
  ],
  "st_louis_missouri_usa": [
    38.6270025,
    -90.19940419999999,
    "St. Louis, MO, USA",
    0.75
  ],
  "boliver_mississippi_usa": [
    33.6598339,
    -91.0531635,
    "Bolivar, MS 38725, USA",
    0.75
  ],
  "shelby_bolivar_mississippi_united_states_of_america": [
    33.9509439,
    -90.76787809999999,
    "Shelby, MS 38774, USA",
    0.75
  ],
  "itta_bena_mississippi_usa": [
    33.49512,
    -90.3198067,
    "Itta Bena, MS 38941, USA",
    0.75
  ],
  "greenville_washington_mississippi_usa": [
    33.399661,
    -91.0377029,
    "Greenville, MS, USA",
    0.75
  ],
  "phoebe_mississippi_usa": [
    33.5847365,
    -88.9495943,
    "Pheba, MS 39755, USA",
    0.75
  ],
  "hillside_cook_county_illinois_united_states_of_america": [
    41.8778084,
    -87.90283980000001,
    "Hillside, IL 60162, USA",
    0.75
  ],
  "chicago_cook_illinois_usa": [
    41.8781136,
    -87.6297982,
    "Chicago, IL, USA",
    0.75
  ],
  "south_carolina_usa": [
    33.836081,
    -81.1637245,
    "South Carolina, USA",
    0.75
  ],
  "franklin_monroe_county_alabama_united_states_of_america": [
    31.7145942,
    -87.4113819,
    "Franklin, AL 36444, USA",
    0.75
  ],
  "winston_mississippi": [
    33.1650338,
    -89.0179332,
    "Winston County, MS, USA",
    0.75
  ],
  "tennessee": [
    35.5174913,
    -86.5804473,
    "Tennessee, USA",
    0.75
  ],
  "ackerman_mississippi": [
    33.3101243,
    -89.17284339999999,
    "Ackerman, MS 39735, USA",
    0.75
  ],
  "ackerman_mississippi_united_states": [
    33.3101243,
    -89.17284339999999,
    "Ackerman, MS 39735, USA",
    0.75
  ],
  "louisiana_united_states": [
    30.5190775,
    -91.5208624,
    "Louisiana, USA",
    0.75
  ],
  "choctaw_mississippi": [
    32.8294273,
    -89.1311937,
    "Choctaw, MS 39350, USA",
    0.75
  ],
  "greenville_west_mississippi": [
    33.399661,
    -91.0377029,
    "Greenville, MS, USA",
    0.75
  ],
  "itta_bena": [
    33.49512,
    -90.3198067,
    "Itta Bena, MS 38941, USA",
    0.75
  ],
  "greenwood_leflore_mississippi_usa": [
    33.5162315,
    -90.1795281,
    "Greenwood, MS, USA",
    0.75
  ],
  "tunica_county_mississippi_usa": [
    34.6407083,
    -90.4125181,
    "Tunica County, MS, USA",
    0.75
  ],
  "shaw_bolivar_mississippi": [
    33.6017815,
    -90.7737075,
    "Shaw, MS 38773, USA",
    0.75
  ],
  "milwaukee_milwaukee_wisconsin_united_states_of_america": [
    43.0410344,
    -87.9096783,
    "Milwaukee, WI, USA",
    0.75
  ],
  "dodge_wisconsin": [
    44.1321852,
    -91.5520942,
    "Dodge, WI, USA",
    0.75
  ],
  "_sunflower_mississippi_usa": [
    33.5428954,
    -90.5370327,
    "Sunflower, MS 38778, USA",
    0.75
  ],
  "milwaukee_milwaukee_wisconsin_usa": [
    43.0410344,
    -87.9096783,
    "Milwaukee, WI, USA",
    0.75
  ],
  "sunflower_county_mississippi_usa": [
    33.526164,
    -90.6773046,
    "Sunflower County, MS, USA",
    0.75
  ],
  "moorhead_sunflower_mississippi_usa": [
    33.4501195,
    -90.5056427,
    "Moorhead, MS 38761, USA",
    0.75
  ],
  "louisiana": [
    30.5190775,
    -91.5208624,
    "Louisiana, USA",
    0.75
  ],
  "collinston_louisiana": [
    32.6909704,
    -91.8717943,
    "Collinston, LA 71229, USA",
    0.75
  ],
  "chicago_cook_illinois": [
    41.8781136,
    -87.6297982,
    "Chicago, IL, USA",
    0.75
  ],
  "collinston_morehouse_louisiana_usa": [
    32.6909704,
    -91.8717943,
    "Collinston, LA 71229, USA",
    0.75
  ],
  "hazelhurst_mississippi_usa": [
    31.8604382,
    -90.39592549999999,
    "Hazlehurst, MS 39083, USA",
    0.75
  ],
  "cleveland_bolivar_mississippi_usa": [
    33.7440023,
    -90.7248187,
    "Cleveland, MS 38732, USA",
    0.75
  ],
  "leland_washington_county_mississippi_usa": [
    33.4053949,
    -90.89760070000001,
    "Leland, MS 38756, USA",
    0.75
  ],
  "crete_will_illinois_usa": [
    41.4444791,
    -87.6314312,
    "Crete, IL, USA",
    0.75
  ],
  "leland_washington_mississippi_usa": [
    33.4053949,
    -90.89760070000001,
    "Leland, MS 38756, USA",
    0.75
  ],
  "chicago_cook_illinois_united_states": [
    41.8781136,
    -87.6297982,
    "Chicago, IL, USA",
    0.75
  ],
  "louisiana_usa": [
    30.5190775,
    -91.5208624,
    "Louisiana, USA",
    0.75
  ],
  "collinston_louisiana_usa": [
    32.6909704,
    -91.8717943,
    "Collinston, LA 71229, USA",
    0.75
  ],
  "united_kingdom": [
    55.378051,
    -3.435973,
    "United Kingdom",
    0.75
  ],
  "windsor_more_louisiana": [
    30.5190775,
    -91.5208624,
    "Louisiana, USA",
    0.75
  ],
  "collinston_morehouse_louisiana": [
    32.6909704,
    -91.8717943,
    "Collinston, LA 71229, USA",
    0.75
  ],
  "collinston_morehouse_louisiana_united_states": [
    32.6909704,
    -91.8717943,
    "Collinston, LA 71229, USA",
    0.75
  ],
  "compton_los_angeles_california_usa": [
    33.8959097,
    -118.2243901,
    "Compton, CA, USA",
    0.75
  ],
  "louisana_usa": [
    30.5190775,
    -91.5208624,
    "Louisiana, USA",
    0.75
  ],
  "moorehead_miss": [
    33.4501195,
    -90.5056427,
    "Moorhead, MS 38761, USA",
    0.75
  ],
  "cook_illinois_united_states": [
    41.7376587,
    -87.697554,
    "Cook County, IL, USA",
    0.75
  ],
  "elwood_will_county_illinois_united_states_of_america": [
    41.4039201,
    -88.1117242,
    "Elwood, IL, USA",
    0.75
  ],
  "morehead_mississippi_usa": [
    33.4501195,
    -90.5056427,
    "Moorhead, MS 38761, USA",
    0.75
  ],
  "fayette_tennessee_usa": [
    35.1520266,
    -86.57055079999999,
    "Fayetteville, TN 37334, USA",
    0.75
  ],
  "indianola_sunflower_mississippi_usa": [
    33.4509513,
    -90.6550917,
    "Indianola, MS 38751, USA",
    0.75
  ],
  "winston_county_mississippi_usa": [
    33.1650338,
    -89.0179332,
    "Winston County, MS, USA",
    0.75
  ],
  "pheba_clay_mississippi": [
    33.5847365,
    -88.9495943,
    "Pheba, MS 39755, USA",
    0.75
  ],
  "beat_2_sunflower_mississippi": [
    33.526164,
    -90.6773046,
    "Sunflower County, MS, USA",
    0.75
  ],
  "ruleville_sunflower_mississippi": [
    33.7259478,
    -90.55148059999999,
    "Ruleville, MS 38771, USA",
    0.75
  ],
  "st_louis_missouri": [
    38.6270025,
    -90.19940419999999,
    "St. Louis, MO, USA",
    0.75
  ],
  "boliver_mississippi": [
    33.6598339,
    -91.0531635,
    "Bolivar, MS 38725, USA",
    0.75
  ],
  "shelby_bolivar_mississippi": [
    33.9509439,
    -90.76787809999999,
    "Shelby, MS 38774, USA",
    0.75
  ],
  "itta_bena_mississippi": [
    33.49512,
    -90.3198067,
    "Itta Bena, MS 38941, USA",
    0.75
  ],
  "greenville_washington_mississippi": [
    33.399661,
    -91.0377029,
    "Greenville, MS, USA",
    0.75
  ],
  "phoebe_mississippi": [
    33.5847365,
    -88.9495943,
    "Pheba, MS 39755, USA",
    0.75
  ],
  "hillside_cook_county_illinois": [
    41.8778084,
    -87.90283980000001,
    "Hillside, IL 60162, USA",
    0.75
  ],
  "south_carolina": [
    33.836081,
    -81.1637245,
    "South Carolina, USA",
    0.75
  ],
  "franklin_monroe_county_alabama": [
    31.7145942,
    -87.4113819,
    "Franklin, AL 36444, USA",
    0.75
  ],
  "greenwood_leflore_mississippi": [
    33.5162315,
    -90.1795281,
    "Greenwood, MS, USA",
    0.75
  ],
  "tunica_county_mississippi": [
    34.6407083,
    -90.4125181,
    "Tunica County, MS, USA",
    0.75
  ],
  "milwaukee_wisconsin": [
    43.0410344,
    -87.9096783,
    "Milwaukee, WI, USA",
    0.75
  ],
  "sunflower_mississippi": [
    33.5428954,
    -90.5370327,
    "Sunflower, MS 38778, USA",
    0.75
  ],
  "sunflower_county_mississippi": [
    33.526164,
    -90.6773046,
    "Sunflower County, MS, USA",
    0.75
  ],
  "moorhead_sunflower_mississippi": [
    33.4501195,
    -90.5056427,
    "Moorhead, MS 38761, USA",
    0.75
  ],
  "hazelhurst_mississippi": [
    31.8604382,
    -90.39592549999999,
    "Hazlehurst, MS 39083, USA",
    0.75
  ],
  "cleveland_bolivar_mississippi": [
    33.7440023,
    -90.7248187,
    "Cleveland, MS 38732, USA",
    0.75
  ],
  "leland_washington_county_mississippi": [
    33.4053949,
    -90.89760070000001,
    "Leland, MS 38756, USA",
    0.75
  ],
  "crete_will_illinois": [
    41.4444791,
    -87.6314312,
    "Crete, IL, USA",
    0.75
  ],
  "leland_washington_mississippi": [
    33.4053949,
    -90.89760070000001,
    "Leland, MS 38756, USA",
    0.75
  ],
  "compton_los_angeles_california": [
    33.8959097,
    -118.2243901,
    "Compton, CA, USA",
    0.75
  ],
  "louisana": [
    30.5190775,
    -91.5208624,
    "Louisiana, USA",
    0.75
  ],
  "elwood_will_county_illinois": [
    41.4039201,
    -88.1117242,
    "Elwood, IL, USA",
    0.75
  ],
  "morehead_mississippi": [
    33.4501195,
    -90.5056427,
    "Moorhead, MS 38761, USA",
    0.75
  ],
  "fayette_tennessee": [
    35.1257427,
    -89.4742177,
    "Fayette County, TN, USA",
    0.75
  ],
  "indianola_sunflower_mississippi": [
    33.4509513,
    -90.6550917,
    "Indianola, MS 38751, USA",
    0.75
  ],
  "winston_county_mississippi": [
    33.1650338,
    -89.0179332,
    "Winston County, MS, USA",
    0.75
  ],
  "saginaw_michigan": [
    43.4195608,
    -83.9473706,
    "Saginaw, MI, USA",
    0.75
  ],
  "noxapater": [
    32.9923505,
    -89.0661736,
    "Noxapater, MS 39346, USA",
    0.75
  ],
  "noxapater_winston_county_mississippi": [
    32.9923505,
    -89.0661736,
    "Noxapater, MS 39346, USA",
    0.75
  ],
  "little_rock_pulaski_arkansas": [
    34.7444618,
    -92.2880157,
    "Little Rock, AR, USA",
    0.75
  ],
  "atlanta_fulton_georgia": [
    33.7501275,
    -84.3885209,
    "Atlanta, GA, USA",
    0.75
  ],
  "lovejoy_ga_": [
    33.4362245,
    -84.3143675,
    "Lovejoy, GA, USA",
    0.75
  ],
  "saginaw_mi": [
    43.4195608,
    -83.9473706,
    "Saginaw, MI, USA",
    0.75
  ],
  "itta_bena_leflore_mississippi": [
    33.49512,
    -90.3198067,
    "Itta Bena, MS 38941, USA",
    0.75
  ],
  "bay_city_bay_michigan": [
    43.5944677,
    -83.8888647,
    "Bay City, MI, USA",
    0.75
  ],
  "saginaw_saginaw_county_michigan": [
    43.4195608,
    -83.9473706,
    "Saginaw, MI, USA",
    0.75
  ],
  "canton_madison_mississippi": [
    32.6126381,
    -90.0367512,
    "Canton, MS, USA",
    0.75
  ],
  "madison_county_mississippi": [
    32.6729459,
    -90.0373201,
    "Madison County, MS, USA",
    0.75
  ],
  "yazoo_county_mississippi": [
    32.8078912,
    -90.37483540000001,
    "Yazoo County, MS, USA",
    0.75
  ],
  "greenwood_mississippi": [
    33.5162315,
    -90.1795281,
    "Greenwood, MS, USA",
    0.75
  ],
  "leflore_mississippi": [
    33.693611,
    -90.054722,
    "Leflore, MS 38940, USA",
    0.75
  ],
  "louisville_winston_mississippi": [
    33.1237377,
    -89.0550624,
    "Louisville, MS 39339, USA",
    0.75
  ],
  "noxapater_winston_mississippi": [
    32.9923505,
    -89.0661736,
    "Noxapater, MS 39346, USA",
    0.75
  ],
  "beat_4_weir_choctaw_county_mississippi": [
    33.2667917,
    -89.29090219999999,
    "Weir, MS 39772, USA",
    0.75
  ],
  "weir_choctaw_mississippi": [
    33.2667917,
    -89.29090219999999,
    "Weir, MS 39772, USA",
    0.75
  ],
  "liberty_chapel_attala_mississippi": [
    33.1937385,
    -89.4847956,
    "Liberty Chapel, MS 39108, USA",
    0.75
  ],
  "weir_choctaw_county_mississippi": [
    33.2667917,
    -89.29090219999999,
    "Weir, MS 39772, USA",
    0.75
  ],
  "ittabena_mississippi": [
    33.49512,
    -90.3198067,
    "Itta Bena, MS 38941, USA",
    0.75
  ],
  "los_angeles": [
    34.0549076,
    -118.242643,
    "Los Angeles, CA, USA",
    0.75
  ],
  "spay_choctaw_mississippi": [
    32.3546679,
    -89.3985283,
    "Mississippi, USA",
    0.75
  ],
  "shellmound_leflore_county_mississippi": [
    33.606853,
    -90.27147699999999,
    "Shellmound, MS 38952, USA",
    0.75
  ],
  "los_angeles_ca": [
    34.0549076,
    -118.242643,
    "Los Angeles, CA, USA",
    0.75
  ],
  "haley_arkansas": [
    33.5356678,
    -91.3248387,
    "Halley, AR 71638, USA",
    0.75
  ],
  "los_angeles_california": [
    34.0549076,
    -118.242643,
    "Los Angeles, CA, USA",
    0.75
  ],
  "marquette_marquette_county_michigan": [
    46.5436199,
    -87.3953713,
    "Marquette, MI 49855, USA",
    0.75
  ],
  "kensett_white_arkansas": [
    35.2334187,
    -91.668385,
    "Kensett, AR, USA",
    0.75
  ],
  "ann_arbor_washtenaw_michigan": [
    42.2808256,
    -83.7430378,
    "Ann Arbor, MI, USA",
    0.75
  ],
  "london_monroe_county_michigan": [
    42.0200442,
    -83.6132701,
    "London, MI 48159, USA",
    0.75
  ],
  "ypsilanti_washtenaw_michigan": [
    42.2411499,
    -83.61299389999999,
    "Ypsilanti, MI, USA",
    0.75
  ],
  "woodruff_county_arkansas": [
    35.1215846,
    -91.13530200000001,
    "Woodruff County, AR, USA",
    0.75
  ],
  "kensett_white_arkansas_united_states": [
    35.2334187,
    -91.668385,
    "Kensett, AR, USA",
    0.75
  ],
  "judsonia_arkansas_white_arkansas": [
    35.2830301,
    -91.6364649,
    "Judsonia, AR 72081, USA",
    0.75
  ],
  "detroit_wayne_michigan": [
    42.32971819999999,
    -83.0424533,
    "Detroit, MI, USA",
    0.75
  ],
  "judoonia_whi_arkansas": [
    35.20105,
    -91.8318334,
    "Arkansas, USA",
    0.75
  ],
  "judsonia_white_arkansas": [
    35.2830301,
    -91.6364649,
    "Judsonia, AR 72081, USA",
    0.75
  ],
  "ann_arbor_washtenaw_michigan_united_states": [
    42.2808256,
    -83.7430378,
    "Ann Arbor, MI, USA",
    0.75
  ],
  "danville_pittsylvania_county_virginia": [
    36.6216097,
    -79.3650549,
    "Danville Expressway, Virginia, USA",
    0.75
  ],
  "madisonville_cincinnati_hamilton_ohio": [
    39.1606159,
    -84.3931327,
    "Madisonville, Cincinnati, OH 45227, USA",
    0.75
  ],
  "judsonia_ar": [
    35.2830301,
    -91.6364649,
    "Judsonia, AR 72081, USA",
    0.75
  ],
  "judsonia_white_arkansas_united_states": [
    35.2830301,
    -91.6364649,
    "Judsonia, AR 72081, USA",
    0.75
  ],
  "ypsilanti_mi": [
    42.2411499,
    -83.61299389999999,
    "Ypsilanti, MI, USA",
    0.75
  ],
  "cook_county_il": [
    41.7376587,
    -87.697554,
    "Cook County, IL, USA",
    0.75
  ],
  "stallo_neshoba_county_mississippi": [
    32.92,
    -89.100556,
    "Stallo, MS 39350, USA",
    0.75
  ],
  "kemper_county_mississippi": [
    32.8018452,
    -88.7108964,
    "Kemper County, MS, USA",
    0.75
  ],
  "stallo_neshoba_mississippi": [
    32.92,
    -89.100556,
    "Stallo, MS 39350, USA",
    0.75
  ],
  "philadelphia_neshoba_mississippi": [
    32.7715227,
    -89.1167275,
    "Philadelphia, MS 39350, USA",
    0.75
  ],
  "beat_5_winston_mississippi": [
    33.1650338,
    -89.0179332,
    "Winston County, MS, USA",
    0.75
  ],
  "community_general_hospital_harrisburg_pa": [
    40.2842662,
    -76.8172855,
    "4300 Londonderry Rd, Harrisburg, PA 17109, USA",
    1.0
  ],
  "louisville_mississippi": [
    33.1237377,
    -89.0550624,
    "Louisville, MS 39339, USA",
    0.75
  ],
  "cibolo_guadalupe_texas": [
    29.5604156,
    -98.2263431,
    "Cibolo, TX, USA",
    0.75
  ],
  "hinze_mississippi": [
    33.0329063,
    -89.2703468,
    "Hinze, MS 39108, USA",
    0.75
  ],
  "harrisburg_dauphin_pennsylvania": [
    40.2731911,
    -76.8867008,
    "Harrisburg, PA, USA",
    0.75
  ],
  "louisville_winston_county_mississippi": [
    33.1237377,
    -89.0550624,
    "Louisville, MS 39339, USA",
    0.75
  ],
  "taft_kern_california": [
    35.1424671,
    -119.4565078,
    "Taft, CA, USA",
    0.75
  ],
  "harrisburg_dauphin_county_pennsylvania": [
    40.2731911,
    -76.8867008,
    "Harrisburg, PA, USA",
    0.75
  ],
  "philadelphia_pennsylvania": [
    39.9525839,
    -75.1652215,
    "Philadelphia, PA, USA",
    0.75
  ],
  "gary_lake_indiana": [
    41.6020403,
    -87.3371523,
    "Gary, IN, USA",
    0.75
  ],
  "jackson_rankin_mississippi": [
    32.2981392,
    -90.18065,
    "Jackson, MS, USA",
    0.75
  ],
  "virginia": [
    37.4315734,
    -78.6568942,
    "Virginia, USA",
    0.75
  ],
  "battle_creek_calhoun_michigan": [
    42.3211522,
    -85.17971419999999,
    "Battle Creek, MI, USA",
    0.75
  ],
  "east_saint_louis_st_clair_county_illinois": [
    38.624514,
    -90.1506465,
    "East St Louis, IL, USA",
    0.75
  ],
  "helena_phillips_arkansas": [
    34.5291892,
    -90.5911996,
    "Helena-West Helena, AR, USA",
    0.75
  ],
  "lincoln_arkansas": [
    35.9475984,
    -94.4234685,
    "Lincoln, AR 72744, USA",
    0.75
  ],
  "phillips_arkansas": [
    34.4611206,
    -90.86751339999999,
    "Phillips County, AR, USA",
    0.75
  ],
  "north_carolina": [
    35.7595731,
    -79.01929969999999,
    "North Carolina, USA",
    0.75
  ],
  "phllips_arkansas": [
    34.4611206,
    -90.86751339999999,
    "Phillips County, AR, USA",
    0.75
  ],
  "halifax_county_virginia": [
    36.6945049,
    -78.9288242,
    "Halifax County, VA, USA",
    0.75
  ],
  "chatham_pittsylvania_virginia": [
    36.82569429999999,
    -79.3980806,
    "Chatham, VA 24531, USA",
    0.75
  ],
  "danville_spotsylvania_county_virginia": [
    38.204165,
    -77.6077865,
    "Spotsylvania County, VA, USA",
    0.75
  ],
  "brown_county_ohio": [
    38.9092089,
    -83.8473015,
    "Brown County, OH, USA",
    0.75
  ],
  "greenwood_leflore_county_mississippi": [
    33.5162315,
    -90.1795281,
    "Greenwood, MS, USA",
    0.75
  ],
  "halifax_virginia": [
    36.7659709,
    -78.92834409999999,
    "Halifax, VA, USA",
    0.75
  ],
  "mecklenburg_virginia": [
    36.6421724,
    -78.3842227,
    "Mecklenburg County, VA, USA",
    0.75
  ],
  "danville_pittsylvania_virginia_united_states": [
    36.5859718,
    -79.39502279999999,
    "Danville, VA, USA",
    0.75
  ],
  "brunswick_county_virginia": [
    36.7570589,
    -77.8367282,
    "Brunswick County, VA, USA",
    0.75
  ],
  "virginia_united_states": [
    37.4315734,
    -78.6568942,
    "Virginia, USA",
    0.75
  ],
  "bedford_county_virginia": [
    37.2538794,
    -79.4703885,
    "Bedford County, VA, USA",
    0.75
  ],
  "pennsylvania": [
    41.2033216,
    -77.1945247,
    "Pennsylvania, USA",
    0.75
  ],
  "ohio_united_states": [
    40.4172871,
    -82.90712300000001,
    "Ohio, USA",
    0.75
  ],
  "mecklenburg_virginia_united_states": [
    36.6421724,
    -78.3842227,
    "Mecklenburg County, VA, USA",
    0.75
  ],
  "charles_city_county_virginia": [
    37.4018216,
    -77.1485163,
    "Charles City County, VA, USA",
    0.75
  ],
  "wilmington_new_castle_delaware_united_states": [
    39.744655,
    -75.5483909,
    "Wilmington, DE, USA",
    0.75
  ],
  "orange_north_carolina_united_states": [
    36.0263022,
    -79.1096901,
    "Orange County, NC, USA",
    0.75
  ],
  "macon_noxubee_mississippi": [
    33.1054039,
    -88.5608767,
    "Macon, MS 39341, USA",
    0.75
  ],
  "kosciusko_attala_mississippi_united_states": [
    33.0576295,
    -89.58757639999999,
    "Kosciusko, MS 39090, USA",
    0.75
  ],
  "ft_gibson_oklahoma_united_states": [
    35.7975986,
    -95.25051730000001,
    "Fort Gibson, OK 74434, USA",
    0.75
  ],
  "south_carolina_u_s_a": [
    33.836081,
    -81.1637245,
    "South Carolina, USA",
    0.75
  ],
  "colleton_county_south_carolina_u_s_a": [
    32.8242297,
    -80.7214417,
    "Colleton County, SC, USA",
    0.75
  ],
  "carroll_georgia_united_states": [
    33.5642239,
    -85.0649071,
    "Carroll County, GA, USA",
    0.75
  ],
  "kite_family_cemetery_on_farm_outside_of_weir_ms_choctaw_co_ms": [
    33.2667917,
    -89.29090219999999,
    "Weir, MS 39772, USA",
    0.75
  ],
  "west_armuchee_walker_georgia": [
    34.6315949,
    -85.1951633,
    "W Armuchee Rd, Georgia, USA",
    0.75
  ],
  "kosciusko_attala_mississippi": [
    33.0576295,
    -89.58757639999999,
    "Kosciusko, MS 39090, USA",
    0.75
  ],
  "ackerman_choctaw_mississippi": [
    33.3101243,
    -89.17284339999999,
    "Ackerman, MS 39735, USA",
    0.75
  ],
  "choctaw_county_mississippi": [
    33.3914427,
    -89.28472510000002,
    "Choctaw County, MS, USA",
    0.75
  ],
  "poplar_creek_choctaw_mississippi": [
    33.351944,
    -89.555556,
    "Poplar Creek, MS 39747, USA",
    0.75
  ],
  "barnwell_south_carolina_united_states": [
    33.2448733,
    -81.3587177,
    "Barnwell, SC 29812, USA",
    0.75
  ],
  "attala_county_mississippi": [
    33.1683267,
    -89.62516459999999,
    "Attala County, MS, USA",
    0.75
  ],
  "cabarrus_county_north_carolina": [
    35.4168123,
    -80.5882803,
    "Cabarrus County, NC, USA",
    0.75
  ],
  "burke_county_north_carolina": [
    35.7616931,
    -81.73494199999999,
    "Burke County, NC, USA",
    0.75
  ],
  "weir_choctaw_mississippi_united_states": [
    33.2667917,
    -89.29090219999999,
    "Weir, MS 39772, USA",
    0.75
  ],
  "mccool_attala_mississippi": [
    33.2020707,
    -89.34507029999999,
    "McCool, MS 39108, USA",
    0.75
  ],
  "evanston_cook_illinois": [
    42.0568276,
    -87.6872172,
    "Evanston, IL, USA",
    0.75
  ],
  "attala_mississippi": [
    33.1683267,
    -89.62516459999999,
    "Attala County, MS, USA",
    0.75
  ],
  "northbrook_cook_county_illinois": [
    42.1275267,
    -87.82895479999999,
    "Northbrook, IL 60062, USA",
    0.75
  ],
  "beat_4_choctaw_mississippi": [
    32.8294273,
    -89.1311937,
    "Choctaw, MS 39350, USA",
    0.75
  ],
  "fancher_hill": [
    42.2805218,
    -78.9694943,
    "Fancher Hill Rd, Leon, NY 14719, USA",
    0.75
  ],
  "illinois": [
    40.6331249,
    -89.3985283,
    "Illinois, USA",
    0.75
  ],
  "ackerman_choctaw_county_mississippi": [
    33.3101243,
    -89.17284339999999,
    "Ackerman, MS 39735, USA",
    0.75
  ],
  "kilmichael_montgomery_mississippi": [
    33.4434573,
    -89.57174309999999,
    "Kilmichael, MS 39747, USA",
    0.75
  ],
  "fayette_county_georgia": [
    33.4502206,
    -84.4802606,
    "Fayette County, GA, USA",
    0.75
  ],
  "pontiac_michigan": [
    42.6389216,
    -83.29104679999999,
    "Pontiac, MI, USA",
    0.75
  ],
  "beat_4_choctaw_county_mississippi": [
    33.3914427,
    -89.28472510000002,
    "Choctaw County, MS, USA",
    0.75
  ],
  "pitt_north_carolina_united_states": [
    35.5589221,
    -77.4242972,
    "Pitt County, NC, USA",
    0.75
  ],
  "gwinnett_georgia_united_states": [
    33.9190653,
    -84.01674229999999,
    "Gwinnett County, GA, USA",
    0.75
  ],
  "macon_county_georgia": [
    32.3523607,
    -84.05902900000001,
    "Macon County, GA, USA",
    0.75
  ],
  "redding_shasta_california": [
    40.5754129,
    -122.3836121,
    "Redding, CA, USA",
    0.75
  ],
  "georgia": [
    42.315407,
    43.35689199999999,
    "Georgia",
    0.75
  ],
  "gwinnett_county_georgia": [
    33.9190653,
    -84.01674229999999,
    "Gwinnett County, GA, USA",
    0.75
  ],
  "alton_madison_illinois": [
    38.6818797,
    -90.1521665,
    "Alton Ave, Madison, IL 62060, USA",
    0.75
  ],
  "alabama_united_states": [
    32.3182314,
    -86.902298,
    "Alabama, USA",
    0.75
  ],
  "edgecombe_north_carolina_united_states": [
    35.8840053,
    -77.6536125,
    "Edgecombe County, NC, USA",
    0.75
  ],
  "halifax_north_carolina_united_states": [
    36.328486,
    -77.5894199,
    "Halifax, NC 27839, USA",
    0.75
  ],
  "pitt_county_north_carolina": [
    35.5589221,
    -77.4242972,
    "Pitt County, NC, USA",
    0.75
  ],
  "floyd_county_georgia": [
    34.2828967,
    -85.2308414,
    "Floyd County, GA, USA",
    0.75
  ],
  "tishomingo_mississippi_united_states": [
    34.6367608,
    -88.23171029999999,
    "Tishomingo, MS 38873, USA",
    0.75
  ],
  "texas": [
    31.9685988,
    -99.9018131,
    "Texas, USA",
    0.75
  ],
  "east_st_louis_st_clair_county_illinois": [
    38.624514,
    -90.1506465,
    "East St Louis, IL, USA",
    0.75
  ],
  "shuqualak_noxubee_mississippi": [
    32.9784616,
    -88.57004289999999,
    "Shuqualak, MS 39361, USA",
    0.75
  ],
  "millstadt_st_clair_county_illinois": [
    38.4614404,
    -90.09177550000001,
    "Millstadt, IL 62260, USA",
    0.75
  ],
  "jones_county_mississippi": [
    31.5343241,
    -89.1705998,
    "Jones County, MS, USA",
    0.75
  ],
  "de_kalb_kemper_mississippi": [
    32.7676329,
    -88.6508784,
    "De Kalb, MS 39328, USA",
    0.75
  ],
  "nashville_berrien_georgia": [
    31.2074197,
    -83.25015479999999,
    "Nashville, GA 31639, USA",
    0.75
  ],
  "neshoba_county_mississippi": [
    32.8057157,
    -89.1705998,
    "Neshoba County, MS, USA",
    0.75
  ],
  "philadelphia_county_pennsylvania": [
    40.0152766,
    -75.1311874,
    "Philadelphia County, Philadelphia, PA, USA",
    0.75
  ],
  "gholson_noxubee_county_mississippi": [
    32.9365181,
    -88.73393809999999,
    "Gholson, MS 39361, USA",
    0.75
  ],
  "noxubee_county_mississippi": [
    33.1605608,
    -88.55653099999999,
    "Noxubee County, MS, USA",
    0.75
  ],
  "pontiac_oakland_michigan": [
    42.6389216,
    -83.29104679999999,
    "Pontiac, MI, USA",
    0.75
  ],
  "chicago_il": [
    41.8781136,
    -87.6297982,
    "Chicago, IL, USA",
    0.75
  ],
  "pontice_michigan": [
    42.6389216,
    -83.29104679999999,
    "Pontiac, MI, USA",
    0.75
  ],
  "high_point_tishomingo_mississippi_united_states": [
    33.188056,
    -89.14611099999999,
    "Highpoint, MS 39339, USA",
    0.75
  ],
  "crockett_houston_texas": [
    31.3177591,
    -95.4571905,
    "Crockett, TX 75835, USA",
    0.75
  ],
  "houston_county_texas": [
    31.2377559,
    -95.4777811,
    "Houston County, TX, USA",
    0.75
  ],
  "silver_city_humphreys_mississippi": [
    33.0965153,
    -90.4967573,
    "Silver City, MS, USA",
    0.75
  ],
  "attla_county_mississippi": [
    33.1683267,
    -89.62516459999999,
    "Attala County, MS, USA",
    0.75
  ],
  "jackson_hinds_mississippi": [
    32.2981392,
    -90.18065,
    "Jackson, MS, USA",
    0.75
  ],
  "attala_mississippi_united_states": [
    33.1683267,
    -89.62516459999999,
    "Attala County, MS, USA",
    0.75
  ],
  "mccool_mississippi": [
    33.2020707,
    -89.34507029999999,
    "McCool, MS 39108, USA",
    0.75
  ],
  "mccool_mississippi_attala": [
    33.2020707,
    -89.34507029999999,
    "McCool, MS 39108, USA",
    0.75
  ],
  "attala_co_ms": [
    33.1683267,
    -89.62516459999999,
    "Attala County, MS, USA",
    0.75
  ],
  "mississippi_": [
    32.3546679,
    -89.3985283,
    "Mississippi, USA",
    0.75
  ],
  "_car_wreck_lake_charles_la_": [
    30.2265949,
    -93.2173758,
    "Lake Charles, LA, USA",
    0.75
  ],
  "marvell_phillips_arkansas": [
    34.5569568,
    -90.9125471,
    "Marvell, AR 72366, USA",
    0.75
  ],
  "mc_cool_attala_mississippi": [
    33.2020707,
    -89.34507029999999,
    "McCool, MS 39108, USA",
    0.75
  ],
  "carroll_ouachita_arkansas": [
    33.5828512,
    -92.9375739,
    "Ouachita County, AR, USA",
    0.75
  ],
  "bradley_ouachita_county_arkansas": [
    33.5828512,
    -92.9375739,
    "Ouachita County, AR, USA",
    0.75
  ],
  "hinds_county_mississippi": [
    32.2648353,
    -90.37483540000001,
    "Hinds County, MS, USA",
    0.75
  ],
  "chester_county_south_carolina": [
    34.6707995,
    -81.1196075,
    "Chester County, SC, USA",
    0.75
  ],
  "chesterfield_virginia_united_states": [
    37.3770935,
    -77.5049863,
    "Chesterfield, VA, USA",
    0.75
  ],
  "laurens_county_ga": [
    32.433014,
    -82.99316069999999,
    "Laurens County, GA, USA",
    0.75
  ],
  "dorchester_county_maryland": [
    38.4152819,
    -76.17837390000001,
    "Dorchester County, MD, USA",
    0.75
  ],
  "morgan_county_alabama": [
    34.4240875,
    -86.86218269999999,
    "Morgan County, AL, USA",
    0.75
  ],
  "choctaw_co_ms": [
    33.3914427,
    -89.28472510000002,
    "Choctaw County, MS, USA",
    0.75
  ],
  "haywood_north_carolina_united_states": [
    35.624394,
    -82.99316069999999,
    "Haywood County, NC, USA",
    0.75
  ],
  "grenada_county_mississippi": [
    33.7516314,
    -89.81303559999999,
    "Grenada County, MS, USA",
    0.75
  ],
  "carroll_county_georgia": [
    33.5642239,
    -85.0649071,
    "Carroll County, GA, USA",
    0.75
  ],
  "stamps_lafayette_arkansas_united_states": [
    33.361072,
    -93.496578,
    "Stamps, AR 71860, USA",
    0.75
  ],
  "arcadia_alabama": [
    33.2028963,
    -87.49361569999999,
    "Arcadia, Tuscaloosa, AL 35404, USA",
    0.75
  ],
  "bienville_louisiana_united_states": [
    32.3568222,
    -92.98043740000001,
    "Bienville, LA 71008, USA",
    0.75
  ],
  "choctaw_mississippi_united_states": [
    32.8294273,
    -89.1311937,
    "Choctaw, MS 39350, USA",
    0.75
  ],
  "cornelia_habersham_georgia_united_states": [
    34.5114883,
    -83.5271166,
    "Cornelia, GA, USA",
    0.75
  ],
  "jefferson_alabama_united_states": [
    32.3859585,
    -87.9017188,
    "Jefferson, AL, USA",
    0.75
  ],
  "haywood_county_north_carolina": [
    35.624394,
    -82.99316069999999,
    "Haywood County, NC, USA",
    0.75
  ],
  "mecklenburg_north_carolina": [
    35.2632655,
    -80.8543847,
    "Mecklenburg County, NC, USA",
    0.75
  ],
  "haywood_north_carolina": [
    35.624394,
    -82.99316069999999,
    "Haywood County, NC, USA",
    0.75
  ],
  "laurens_georgia": [
    32.433014,
    -82.99316069999999,
    "Laurens County, GA, USA",
    0.75
  ],
  "south_carolina_united_states": [
    33.836081,
    -81.1637245,
    "South Carolina, USA",
    0.75
  ],
  "chesterfield_south_carolina": [
    34.7359889,
    -80.0881194,
    "Chesterfield, SC 29709, USA",
    0.75
  ],
  "anson_county_north_carolina": [
    34.9054732,
    -80.1875065,
    "Anson County, NC, USA",
    0.75
  ],
  "cobb_county_georgia": [
    33.8999297,
    -84.56414699999999,
    "Cobb County, GA, USA",
    0.75
  ],
  "tarboro_edgecombe_north_carolina": [
    35.8968236,
    -77.5358049,
    "Tarboro, NC 27886, USA",
    0.75
  ],
  "dekalb_county_georgia": [
    33.7956441,
    -84.2278796,
    "Dekalb County, GA, USA",
    0.75
  ],
  "buncomb_county_north_carolina": [
    35.59313770000001,
    -82.4752757,
    "Buncombe County, NC, USA",
    0.75
  ],
  "mecklenburg_county_north_carolina": [
    35.2632655,
    -80.8543847,
    "Mecklenburg County, NC, USA",
    0.75
  ],
  "shreveport_caddo_louisiana": [
    32.5130159,
    -93.7514874,
    "Shreveport, LA, USA",
    0.75
  ],
  "bradley_tennessee": [
    35.1937778,
    -84.8567932,
    "Bradley County, TN, USA",
    0.75
  ],
  "cabarrus_county_nc": [
    35.4168123,
    -80.5882803,
    "Cabarrus County, NC, USA",
    0.75
  ],
  "dent_county_mo": [
    37.544666,
    -91.44346900000001,
    "Dent County, MO, USA",
    0.75
  ],
  "jonathan_creek_haywood_co_north_carolina": [
    35.5639129,
    -83.0205066,
    "Jonathan Creek Rd, North Carolina 28785, USA",
    0.75
  ],
  "tarboro_edgecombe_north_carolina_united_states": [
    35.8968236,
    -77.5358049,
    "Tarboro, NC 27886, USA",
    0.75
  ],
  "cabarrus_north_carolina_united_states": [
    35.4168123,
    -80.5882803,
    "Cabarrus County, NC, USA",
    0.75
  ],
  "isle_of_wight_virginia_united_states": [
    36.908286,
    -76.7065346,
    "Isle of Wight, VA, USA",
    0.75
  ],
  "herrick_creek_edgecombe_north_carolina": [
    35.8840053,
    -77.6536125,
    "Edgecombe County, NC, USA",
    0.75
  ],
  "cheraw_chesterfield_south_carolina_united_states": [
    34.6976564,
    -79.8833971,
    "Cheraw, SC 29520, USA",
    0.75
  ],
  "barnwell_south_carolina": [
    33.2448733,
    -81.3587177,
    "Barnwell, SC 29812, USA",
    0.75
  ],
  "cherokee_county_alabama": [
    34.1665322,
    -85.684578,
    "Cherokee County, AL, USA",
    0.75
  ],
  "camden_wilcox_alabama_united_states": [
    31.9909813,
    -87.2905456,
    "Camden, AL 36726, USA",
    0.75
  ],
  "jackson_alabama_united_states": [
    31.5090521,
    -87.8944435,
    "Jackson, AL 36545, USA",
    0.75
  ],
  "montgomery_county_arkansas": [
    34.5424074,
    -93.66232389999999,
    "Montgomery County, AR, USA",
    0.75
  ],
  "gordon_al": [
    31.14129179999999,
    -85.09659649999999,
    "Gordon, AL 36343, USA",
    0.75
  ],
  "mecklenburg_nc": [
    35.2632655,
    -80.8543847,
    "Mecklenburg County, NC, USA",
    0.75
  ],
  "gordon_co_ga": [
    34.4891699,
    -84.8567932,
    "Gordon County, GA, USA",
    0.75
  ],
  "cabarrus_north_carolina": [
    35.4168123,
    -80.5882803,
    "Cabarrus County, NC, USA",
    0.75
  ],
  "south_fork_twp_montgomery_co_ar": [
    34.5424074,
    -93.66232389999999,
    "Montgomery County, AR, USA",
    0.75
  ],
  "jackson_co_al": [
    34.7090388,
    -86.0121573,
    "Jackson County, AL, USA",
    0.75
  ],
  "concord_cabarrus_co_nc": [
    35.4100756,
    -80.5819527,
    "Concord, NC, USA",
    0.75
  ],
  "fulton_county_georgia": [
    33.8033965,
    -84.3962535,
    "Fulton County, GA, USA",
    0.75
  ],
  "duluth_gwinnett_county_georgia": [
    34.0028786,
    -84.1446376,
    "Duluth, GA, USA",
    0.75
  ],
  "mecklenburg_north_carolina_united_states": [
    35.2632655,
    -80.8543847,
    "Mecklenburg County, NC, USA",
    0.75
  ],
  "randolph_county_alabama": [
    33.2681523,
    -85.52002399999999,
    "Randolph County, AL, USA",
    0.75
  ],
  "isle_of_wight_virginia": [
    36.908286,
    -76.7065346,
    "Isle of Wight, VA, USA",
    0.75
  ],
  "edgecombe_north_carolina": [
    35.8840053,
    -77.6536125,
    "Edgecombe County, NC, USA",
    0.75
  ],
  "catmere_end_essex_massachusetts_united_states": [
    42.63195820000001,
    -70.7829315,
    "Essex, MA, USA",
    0.75
  ],
  "catmere_end_essex_massachusetts": [
    42.4072107,
    -71.3824374,
    "Massachusetts, USA",
    0.75
  ],
  "surry_county_north_carolina": [
    36.3743453,
    -80.6770787,
    "Surry County, NC, USA",
    0.75
  ],
  "bertie_north_carolina_united_states": [
    36.0245185,
    -76.964306,
    "Bertie County, NC, USA",
    0.75
  ],
  "nc": [
    35.7595731,
    -79.01929969999999,
    "North Carolina, USA",
    0.75
  ],
  "mississppi": [
    32.3546679,
    -89.3985283,
    "Mississippi, USA",
    0.75
  ],
  "mcool_ms": [
    33.2020707,
    -89.34507029999999,
    "McCool, MS 39108, USA",
    0.75
  ],
  "norfolk_virginia": [
    36.8507689,
    -76.28587259999999,
    "Norfolk, VA, USA",
    0.75
  ],
  "township_17_range_9_choctaw_mississippi": [
    32.8294273,
    -89.1311937,
    "Choctaw, MS 39350, USA",
    0.75
  ],
  "webb_tallahatchie_mississippi": [
    33.9473356,
    -90.34425759999999,
    "Webb, MS, USA",
    0.75
  ],
  "french_camp_choctaw_mississippi": [
    33.293181,
    -89.3995159,
    "French Camp, MS 39745, USA",
    0.75
  ],
  "leflore_county_mississippi": [
    33.5274427,
    -90.37483540000001,
    "Leflore County, MS, USA",
    0.75
  ],
  "vineland_mar_alabama": [
    32.037334,
    -87.660156,
    "Vineland, AL 36784, USA",
    0.75
  ],
  "bessemer_jefferson_alabama": [
    33.4017766,
    -86.954437,
    "Bessemer, AL, USA",
    0.75
  ],
  "shiloh_marengo_alabama": [
    32.127831,
    -87.734993,
    "Shiloh, AL 36754, USA",
    0.75
  ],
  "demopolis_marengo_alabama": [
    32.5176361,
    -87.83640199999999,
    "Demopolis, AL, USA",
    0.75
  ],
  "birmingham_al": [
    33.5185892,
    -86.8103567,
    "Birmingham, AL, USA",
    0.75
  ],
  "allen_alabama": [
    33.9151043,
    -87.74168759999999,
    "Glen Allen, AL, USA",
    0.75
  ],
  "indianapolis_marion_indiana": [
    39.76909,
    -86.158018,
    "Indianapolis, IN, USA",
    0.75
  ],
  "rolla_phelps_missouri": [
    37.948544,
    -91.7715303,
    "Rolla, MO, USA",
    0.75
  ],
  "gasconade_missouri": [
    38.669489,
    -91.5601667,
    "Gasconade, MO, USA",
    0.75
  ],
  "bent_arkansas": [
    34.5693083,
    -92.58537799999999,
    "Benton, AR, USA",
    0.75
  ],
  "mammoth_springs_fulton_county_arkansas": [
    36.4956312,
    -91.5404401,
    "Mammoth Spring, AR 72554, USA",
    0.75
  ],
  "pine_bluff_jefferson_county_arkansas": [
    34.224908,
    -92.0033977,
    "Pine Bluff, AR, USA",
    0.75
  ],
  "jackson_co_tennessee": [
    36.4004931,
    -85.64348700000001,
    "Jackson County, TN, USA",
    0.75
  ],
  "ravenden_lawrence_county_arkansas": [
    36.236677,
    -91.2526455,
    "Ravenden, AR 72459, USA",
    0.75
  ],
  "fentress_jackson_tennessee": [
    35.6145169,
    -88.81394689999999,
    "Jackson, TN, USA",
    0.75
  ],
  "ravenden_lawrence_arkansas": [
    36.236677,
    -91.2526455,
    "Ravenden, AR 72459, USA",
    0.75
  ],
  "jackson_county_tennessee": [
    36.4004931,
    -85.64348700000001,
    "Jackson County, TN, USA",
    0.75
  ],
  "trumann_poinsett_county_arkansas": [
    35.6785986,
    -90.5241357,
    "Trumann, AR 72472, USA",
    0.75
  ],
  "rolla_phelps_missouri_united_states": [
    37.948544,
    -91.7715303,
    "Rolla, MO, USA",
    0.75
  ],
  "san_gabriel_los_angeles_california_united_states": [
    34.09611110000001,
    -118.1058333,
    "San Gabriel, CA, USA",
    0.75
  ],
  "lawrence_county_arkansas": [
    35.9969735,
    -91.13530200000001,
    "Lawrence County, AR, USA",
    0.75
  ],
  "ravenden_randolph_arkansas_united_states": [
    36.236677,
    -91.2526455,
    "Ravenden, AR 72459, USA",
    0.75
  ],
  "sulphur_rock_independence_arkansas_united_states": [
    35.7535137,
    -91.5008583,
    "Sulphur Rock, AR 72579, USA",
    0.75
  ],
  "hilham_jackson_tennessee": [
    36.4142281,
    -85.4416363,
    "Hilham, TN, USA",
    0.75
  ],
  "pacific_franklin_county_missouri": [
    38.4819976,
    -90.7415194,
    "Pacific, MO 63069, USA",
    0.75
  ],
  "tennessee_united_states": [
    35.5174913,
    -86.5804473,
    "Tennessee, USA",
    0.75
  ],
  "oregon_county_missouri": [
    36.6870089,
    -91.44346900000001,
    "Oregon County, MO, USA",
    0.75
  ],
  "pine_bluff_jefferson_arkansas": [
    34.224908,
    -92.0033977,
    "Pine Bluff, AR, USA",
    0.75
  ],
  "holla_bend_yell_county_arkansas": [
    35.1750733,
    -93.07624770000001,
    "Holla Bend, Arkansas, USA",
    0.75
  ],
  "ravenden_springs_randolph_county_arkansas": [
    36.3165817,
    -91.2250119,
    "Ravenden Springs, AR 72460, USA",
    0.75
  ],
  "johnson_arkansas": [
    36.1334622,
    -94.1629938,
    "Johnson, AR, USA",
    0.75
  ],
  "holla_bend_pope_arkansas": [
    35.16611,
    -93.05167,
    "Holla Bend, AR 72858, USA",
    0.75
  ],
  "st_joe_polk_arkansas": [
    36.03029920000001,
    -92.8054916,
    "St Joe, AR 72675, USA",
    0.75
  ],
  "barbadoes_w_i": [
    13.193887,
    -59.543198,
    "Barbados",
    0.75
  ],
  "maryland": [
    39.0457549,
    -76.64127119999999,
    "Maryland, USA",
    0.75
  ],
  "leava_ms": [
    -14.2968356,
    -178.1581081,
    "Leava, Wallis and Futuna",
    0.75
  ],
  "terre_haute_vigo_indiana": [
    39.4654441,
    -87.41394269999999,
    "Terre Haute, IN, USA",
    0.75
  ],
  "miamisburg_montgomery": [
    39.6417046,
    -84.2878683,
    "Miamisburg, OH, USA",
    0.75
  ],
  "dayton_montgomery_county_ohio": [
    39.7592225,
    -84.1936144,
    "Dayton, OH, USA",
    0.75
  ],
  "yazoo_city_mississippi": [
    32.8551326,
    -90.4056468,
    "Yazoo City, MS 39194, USA",
    0.75
  ],
  "ms_choctaw_co_": [
    33.3914427,
    -89.28472510000002,
    "Choctaw County, MS, USA",
    0.75
  ],
  "louisville_w_mississippi": [
    33.1237377,
    -89.0550624,
    "Louisville, MS 39339, USA",
    0.75
  ],
  "detroit_districts_501_750_detroit_wayne_michigan": [
    42.3366972,
    -83.0550303,
    "Detroit, MI 48201, USA",
    0.75
  ],
  "kennard_houston_texas_united_states": [
    31.3595701,
    -95.1846665,
    "Kennard, TX 75847, USA",
    0.75
  ],
  "pennington_trinity_texas_united_states": [
    31.1912941,
    -95.23549369999999,
    "Pennington, TX 75845, USA",
    0.75
  ],
  "san_francisco_san_mateo_california": [
    37.5629917,
    -122.3255254,
    "San Mateo, CA, USA",
    0.75
  ],
  "texas_united_states": [
    31.9685988,
    -99.9018131,
    "Texas, USA",
    0.75
  ],
  "crockett_houston_texas_united_states": [
    31.3177591,
    -95.4571905,
    "Crockett, TX 75835, USA",
    0.75
  ],
  "chicago_cook_co_illinois": [
    41.8781136,
    -87.6297982,
    "Chicago, IL, USA",
    0.75
  ],
  "weir_mississippi": [
    33.2667917,
    -89.29090219999999,
    "Weir, MS 39772, USA",
    0.75
  ],
  "stewart_montgomery_mississippi": [
    33.4506793,
    -89.43618339999999,
    "Stewart, MS 39767, USA",
    0.75
  ],
  "montgomery_county_mississippi": [
    33.5274427,
    -89.62516459999999,
    "Montgomery County, MS, USA",
    0.75
  ],
  "kensett_whit_arkansas": [
    35.2334187,
    -91.668385,
    "Kensett, AR, USA",
    0.75
  ],
  "missouri": [
    37.9642529,
    -91.8318334,
    "Missouri, USA",
    0.75
  ],
  "glenmora_rapides_louisiana": [
    30.9765797,
    -92.5851402,
    "Glenmora, LA 71433, USA",
    0.75
  ],
  "cleveland_cuyahoga_ohio": [
    41.49932,
    -81.6943605,
    "Cleveland, OH, USA",
    0.75
  ],
  "parma_cuyahoga_ohio": [
    41.4047742,
    -81.7229086,
    "Parma, OH, USA",
    0.75
  ],
  "cleveland_heights_cuyahoga_ohio": [
    41.5200518,
    -81.556235,
    "Cleveland Heights, OH, USA",
    0.75
  ],
  "south_holland_cook_illinois": [
    41.6008681,
    -87.60698939999999,
    "South Holland, IL, USA",
    0.75
  ],
  "bossier_city_bossier_louisiana": [
    32.5159852,
    -93.7321228,
    "Bossier City, LA, USA",
    0.75
  ],
  "glendora_tallahatchie_mississippi": [
    33.8292817,
    -90.2931437,
    "Glendora, MS 38928, USA",
    0.75
  ],
  "mccool_attal_mississippi": [
    33.2020707,
    -89.34507029999999,
    "McCool, MS 39108, USA",
    0.75
  ],
  "alameda_california": [
    37.7798721,
    -122.2821855,
    "Alameda, CA, USA",
    0.75
  ],
  "columbia_louisiana": [
    32.1051567,
    -92.0779129,
    "Columbia, LA 71418, USA",
    0.75
  ],
  "columbia_caldwell_louisiana": [
    32.1051567,
    -92.0779129,
    "Columbia, LA 71418, USA",
    0.75
  ],
  "canton_mississippi": [
    32.6126381,
    -90.0367512,
    "Canton, MS, USA",
    0.75
  ],
  "garland_bowie_county_texas": [
    32.9136363,
    -96.6364294,
    "Garland, TX, USA",
    0.75
  ],
  "3210_south_washington_avenue_saginaw_michigan_48601": [
    43.396797,
    -83.955871,
    "3210 S Washington Ave, Saginaw, MI 48601, USA",
    1.0
  ],
  "rodeo_contra_costa_california": [
    38.032977,
    -122.2669138,
    "Rodeo, CA, USA",
    0.75
  ],
  "itta_bena_leflore_county_mississippi": [
    33.49512,
    -90.3198067,
    "Itta Bena, MS 38941, USA",
    0.75
  ],
  "st_louis_city_missouri": [
    38.6270025,
    -90.19940419999999,
    "St. Louis, MO, USA",
    0.75
  ],
  "hillsdale_st_louis_county_missouri": [
    38.685386,
    -90.287593,
    "Hillsdale, MO, USA",
    0.75
  ],
  "atlanta_ga": [
    33.7501275,
    -84.3885209,
    "Atlanta, GA, USA",
    0.75
  ],
  "biggers_ark_ark": [
    36.3323382,
    -90.8067569,
    "Biggers, AR 72413, USA",
    0.75
  ],
  "current_river_randolph_arkansas": [
    36.3457918,
    -90.9820668,
    "Randolph County, AR, USA",
    0.75
  ],
  "biggers_ark": [
    36.3323382,
    -90.8067569,
    "Biggers, AR 72413, USA",
    0.75
  ],
  "biggers_rand_arkansas": [
    36.3323382,
    -90.8067569,
    "Biggers, AR 72413, USA",
    0.75
  ],
  "cotton_plant_woodruff_arkansas": [
    35.0046378,
    -91.250908,
    "Cotton Plant, AR 72036, USA",
    0.75
  ],
  "randolph_county_ar": [
    36.3457918,
    -90.9820668,
    "Randolph County, AR, USA",
    0.75
  ],
  "randolph_arkansas": [
    36.3457918,
    -90.9820668,
    "Randolph County, AR, USA",
    0.75
  ],
  "biggers_randolph_county_arkansas": [
    36.3323382,
    -90.8067569,
    "Biggers, AR 72413, USA",
    0.75
  ],
  "savannah_chatham_county_georgia": [
    32.0808989,
    -81.091203,
    "Savannah, GA, USA",
    0.75
  ],
  "moro_lee_arkansas": [
    34.7965745,
    -90.9900186,
    "Moro, AR, USA",
    0.75
  ],
  "hampton_lee_county_arkansas": [
    33.5379367,
    -92.46979569999999,
    "Hampton, AR 71744, USA",
    0.75
  ],
  "north_chicago_lake_illinois": [
    42.325578,
    -87.8411818,
    "North Chicago, IL, USA",
    0.75
  ],
  "moro_bradley_arkansas": [
    34.7965745,
    -90.9900186,
    "Moro, AR, USA",
    0.75
  ],
  "marianna_arkansas": [
    34.7746203,
    -90.7722536,
    "Marianna, AR 72360, USA",
    0.75
  ],
  "lee_arkansas": [
    34.7712669,
    -90.8294002,
    "Lee County, AR, USA",
    0.75
  ],
  "arkansas_hampton_lee_arkansas": [
    33.5379367,
    -92.46979569999999,
    "Hampton, AR 71744, USA",
    0.75
  ],
  "arkaansas_hampton_lee_arkansas": [
    35.20105,
    -91.8318334,
    "Arkansas, USA",
    0.75
  ],
  "hamptonlee_co_arkansas": [
    35.20105,
    -91.8318334,
    "Arkansas, USA",
    0.75
  ],
  "st_landry_louisiana": [
    30.6036535,
    -92.0665197,
    "St Landry Parish, LA, USA",
    0.75
  ],
  "timbo_stone_county_arkansas": [
    35.8710113,
    -92.3168963,
    "Timbo, AR, USA",
    0.75
  ],
  "alva_woods_county_oklahoma": [
    36.8050308,
    -98.6664737,
    "Alva, OK 73717, USA",
    0.75
  ],
  "detroit_michigan": [
    42.32971819999999,
    -83.0424533,
    "Detroit, MI, USA",
    0.75
  ],
  "ouachita_county_arkansas": [
    33.5828512,
    -92.9375739,
    "Ouachita County, AR, USA",
    0.75
  ],
  "amy_ouachita_arkansas_carroll_township": [
    33.7320525,
    -92.8154404,
    "Amy, AR 71701, USA",
    0.75
  ],
  "buncombe_north_carolina": [
    35.59313770000001,
    -82.4752757,
    "Buncombe County, NC, USA",
    0.75
  ],
  "clyde_haywood_county_north_carolina": [
    35.5334379,
    -82.910691,
    "Clyde, NC 28721, USA",
    0.75
  ],
  "crabtree_haywood_north_carolina": [
    35.6017698,
    -82.94124939999999,
    "Crabtree, NC 28721, USA",
    0.75
  ],
  "haywood_co_nc": [
    35.624394,
    -82.99316069999999,
    "Haywood County, NC, USA",
    0.75
  ],
  "ellijay_gilmer_co_ga": [
    34.6948076,
    -84.4821498,
    "Ellijay, GA, USA",
    0.75
  ],
  "buncombe_co_nc": [
    35.59313770000001,
    -82.4752757,
    "Buncombe County, NC, USA",
    0.75
  ],
  "jonathan_haywood_n_c_": [
    35.7595731,
    -79.01929969999999,
    "North Carolina, USA",
    0.75
  ],
  "asheville_buncombe_n_c_": [
    35.5975104,
    -82.54605629999999,
    "Asheville, NC, USA",
    0.75
  ],
  "waynesville_haywood_north_carolina": [
    35.4887145,
    -82.98874769999999,
    "Waynesville, NC 28786, USA",
    0.75
  ],
  "jonathan_haywood_county_north_carolina": [
    35.624394,
    -82.99316069999999,
    "Haywood County, NC, USA",
    0.75
  ],
  "clarke_county_georgia": [
    33.9519347,
    -83.357567,
    "Clarke County, GA, USA",
    0.75
  ],
  "shelby_county_texas": [
    31.8343021,
    -94.15137639999999,
    "Shelby County, TX, USA",
    0.75
  ],
  "new_orleans_orleans_parish_louisiana": [
    29.9508941,
    -90.07583559999999,
    "New Orleans, LA, USA",
    0.75
  ],
  "los_angeles_los_angeles_county_california": [
    34.0549076,
    -118.242643,
    "Los Angeles, CA, USA",
    0.75
  ],
  "lynchburg_campbell_virginia": [
    37.4148819,
    -79.1422071,
    "Lynchburg, VA, USA",
    0.75
  ],
  "north_carolina_united_states": [
    35.7595731,
    -79.01929969999999,
    "North Carolina, USA",
    0.75
  ],
  "garland_city_ark": [
    33.3579649,
    -93.7108995,
    "Garland City, AR, USA",
    0.75
  ],
  "atkins_pope_arkansas": [
    35.2420396,
    -92.9374471,
    "Atkins, AR, USA",
    0.75
  ],
  "atkins_arkansas": [
    35.2420396,
    -92.9374471,
    "Atkins, AR, USA",
    0.75
  ],
  "fort_smith_sebastian_arkansas": [
    35.3843722,
    -94.42096459999999,
    "Fort Smith, AR, USA",
    0.75
  ],
  "kemper_mississippi_united_states": [
    32.8018452,
    -88.7108964,
    "Kemper County, MS, USA",
    0.75
  ],
  "dekalb_kemper_ms": [
    32.7676329,
    -88.6508784,
    "De Kalb, MS 39328, USA",
    0.75
  ],
  "chicago_cook_il": [
    41.8781136,
    -87.6297982,
    "Chicago, IL, USA",
    0.75
  ],
  "noxubee_mississippi": [
    33.1605608,
    -88.55653099999999,
    "Noxubee County, MS, USA",
    0.75
  ],
  "king_william_virginia_united_states": [
    37.6871635,
    -77.01368389999999,
    "King William, VA, USA",
    0.75
  ],
  "green_georgia_united_states": [
    34.0884316,
    -85.1485603,
    "Green, GA 30173, USA",
    0.75
  ],
  "cleveland_cuyahoga_ohio_united_states": [
    41.49932,
    -81.6943605,
    "Cleveland, OH, USA",
    0.75
  ],
  "livingston_louisiana": [
    30.5021345,
    -90.7478737,
    "Livingston, LA 70754, USA",
    0.75
  ],
  "memphis_tennessee": [
    35.1485812,
    -90.0518955,
    "Memphis, TN, USA",
    0.75
  ],
  "louisville_town_winston_mississippi": [
    33.1237377,
    -89.0550624,
    "Louisville, MS 39339, USA",
    0.75
  ],
  "plattsburg_winston_mississippi": [
    32.9415189,
    -89.19256589999999,
    "Plattsburg, MS 39346, USA",
    0.75
  ],
  "columbus_lowndes_mississippi": [
    33.4956744,
    -88.4272627,
    "Columbus, MS, USA",
    0.75
  ],
  "madison_county_miss": [
    37.5528602,
    -90.37483540000001,
    "Madison County, MO, USA",
    0.75
  ],
  "canton_madison_county_mississippi": [
    32.6126381,
    -90.0367512,
    "Canton, MS, USA",
    0.75
  ],
  "madison_mississippi": [
    32.4618086,
    -90.1153638,
    "Madison, MS 39110, USA",
    0.75
  ],
  "beat_1_madison_mississippi": [
    32.4618086,
    -90.1153638,
    "Madison, MS 39110, USA",
    0.75
  ],
  "canton_ms": [
    32.6126381,
    -90.0367512,
    "Canton, MS, USA",
    0.75
  ],
  "hinds_county_ms": [
    32.2648353,
    -90.37483540000001,
    "Hinds County, MS, USA",
    0.75
  ],
  "canton_madis_mississippi": [
    32.6126381,
    -90.0367512,
    "Canton, MS, USA",
    0.75
  ],
  "marion_county_mississippi": [
    31.1708442,
    -89.77553379999999,
    "Marion County, MS, USA",
    0.75
  ],
  "sandhill_rankin_mississippi": [
    32.4876409,
    -89.8803575,
    "Sand Hill, MS 39047, USA",
    0.75
  ],
  "tallahatchie_county_mississippi": [
    33.9302578,
    -90.1869644,
    "Tallahatchie County, MS, USA",
    0.75
  ],
  "saint_paul_ramsey_minnesota_united_states": [
    44.9537029,
    -93.0899578,
    "St Paul, MN, USA",
    0.75
  ],
  "ohio": [
    40.4172871,
    -82.90712300000001,
    "Ohio, USA",
    0.75
  ],
  "kosciusko_mississippi": [
    33.0576295,
    -89.58757639999999,
    "Kosciusko, MS 39090, USA",
    0.75
  ],
  "south_bend_st_joseph_indiana": [
    41.6763545,
    -86.25198979999999,
    "South Bend, IN, USA",
    0.75
  ],
  "madison_madison_county_mississippi": [
    32.4618086,
    -90.1153638,
    "Madison, MS 39110, USA",
    0.75
  ],
  "indiana": [
    40.5512165,
    -85.60236429999999,
    "Indiana, USA",
    0.75
  ],
  "indiana_united_states": [
    40.5512165,
    -85.60236429999999,
    "Indiana, USA",
    0.75
  ],
  "desoto_mississippi": [
    34.9065453,
    -89.9626799,
    "Desoto County, MS, USA",
    0.75
  ],
  "precinct_1_throckmorton_texas": [
    33.1787153,
    -99.17757560000001,
    "Throckmorton, TX 76483, USA",
    0.75
  ],
  "spay_mississippi": [
    32.3546679,
    -89.3985283,
    "Mississippi, USA",
    0.75
  ],
  "mccool_choct_mississippi": [
    33.1668162,
    -89.2923252,
    "McCool Rd, Mississippi 39108, USA",
    0.75
  ],
  "sacramento_california": [
    38.5781342,
    -121.4944209,
    "Sacramento, CA, USA",
    0.75
  ],
  "mccool_choco_mississippi": [
    33.2020707,
    -89.34507029999999,
    "McCool, MS 39108, USA",
    0.75
  ],
  "saginaw_county_michigan": [
    43.4044253,
    -84.01674229999999,
    "Saginaw County, MI, USA",
    0.75
  ],
  "michigan": [
    44.3148443,
    -85.60236429999999,
    "Michigan, USA",
    0.75
  ],
  "ethelsville_pickens_alabama": [
    33.4156743,
    -88.21669910000001,
    "Ethelsville, AL 35461, USA",
    0.75
  ],
  "mobile_alabama": [
    30.6953657,
    -88.0398912,
    "Mobile, AL, USA",
    0.75
  ],
  "sacramento_sacramento_county_california": [
    38.5781342,
    -121.4944209,
    "Sacramento, CA, USA",
    0.75
  ],
  "mccool_attala_county_mississippi": [
    33.2020707,
    -89.34507029999999,
    "McCool, MS 39108, USA",
    0.75
  ],
  "ridgeland_madison_mississippi": [
    32.4284761,
    -90.1323087,
    "Ridgeland, MS, USA",
    0.75
  ],
  "jackson_hinds_county_mississippi": [
    32.2981392,
    -90.18065,
    "Jackson, MS, USA",
    0.75
  ],
  "sacramento_county_california": [
    38.5747513,
    -121.4813923,
    "Sacramento County, CA, USA",
    0.75
  ],
  "sacramento_ca": [
    38.5781342,
    -121.4944209,
    "Sacramento, CA, USA",
    0.75
  ],
  "ackerman_miss": [
    33.3101243,
    -89.17284339999999,
    "Ackerman, MS 39735, USA",
    0.75
  ],
  "port_huron_st_clair_michigan": [
    42.9708634,
    -82.42491419999999,
    "Port Huron, MI, USA",
    0.75
  ],
  "louisville_miss_": [
    33.1237377,
    -89.0550624,
    "Louisville, MS 39339, USA",
    0.75
  ],
  "brunswick_glynn_county_georgia": [
    31.1510919,
    -81.4878157,
    "Brunswick, GA, USA",
    0.75
  ],
  "port_huron_st_clair_county_michigan": [
    42.9708634,
    -82.42491419999999,
    "Port Huron, MI, USA",
    0.75
  ],
  "new_prospect_ms": [
    32.3546679,
    -89.3985283,
    "Mississippi, USA",
    0.75
  ],
  "moreno_valley_riverside_california": [
    33.9424658,
    -117.2296717,
    "Moreno Valley, CA, USA",
    0.75
  ],
  "california": [
    36.778261,
    -119.4179324,
    "California, USA",
    0.75
  ],
  "mc_cool_mississippi": [
    33.2020707,
    -89.34507029999999,
    "McCool, MS 39108, USA",
    0.75
  ],
  "leon_texas": [
    31.2152685,
    -95.9832577,
    "Leon County, TX, USA",
    0.75
  ],
  "louisvile_wi_mississippi": [
    33.1237377,
    -89.0550624,
    "Louisville, MS 39339, USA",
    0.75
  ],
  "jeffersonville_clark_indiana": [
    38.2775702,
    -85.7371847,
    "Jeffersonville, IN, USA",
    0.75
  ],
  "new_albany_floyd_county_indiana": [
    38.2856247,
    -85.8241312,
    "New Albany, IN 47150, USA",
    0.75
  ],
  "grand_rapids_kent_michigan": [
    42.9704146,
    -85.6721946,
    "Grand Rapids, MI, USA",
    0.75
  ],
  "kentucky": [
    37.8393332,
    -84.2700179,
    "Kentucky, USA",
    0.75
  ],
  "mccool_chact_mississippi": [
    33.2020707,
    -89.34507029999999,
    "McCool, MS 39108, USA",
    0.75
  ],
  "chicago_city_cook_illinois": [
    41.8781136,
    -87.6297982,
    "Chicago, IL, USA",
    0.75
  ],
  "hattisburg_mississippi": [
    31.3271189,
    -89.29033919999999,
    "Hattiesburg, MS, USA",
    0.75
  ],
  "denver_colorado": [
    39.7392358,
    -104.990251,
    "Denver, CO, USA",
    0.75
  ],
  "natchez_adams_county_mississippi": [
    31.5604442,
    -91.40317100000001,
    "Natchez, MS 39120, USA",
    0.75
  ],
  "clarksdale_coahoma_mississippi": [
    34.2001086,
    -90.5709323,
    "Clarksdale, MS, USA",
    0.75
  ],
  "pickens_alabama": [
    33.3339954,
    -88.0900762,
    "Pickens County, AL, USA",
    0.75
  ],
  "new_hope_lowndes_mississippi": [
    33.446728,
    -88.32636029999999,
    "New Hope, MS 39702, USA",
    0.75
  ],
  "ethelsville_pickens_county_alabama": [
    33.4156743,
    -88.21669910000001,
    "Ethelsville, AL 35461, USA",
    0.75
  ],
  "lamar_co_alabama": [
    33.6923649,
    -88.0900762,
    "Lamar County, AL, USA",
    0.75
  ],
  "bibb_alabama": [
    32.9562798,
    -87.14228949999999,
    "Bibb County, AL, USA",
    0.75
  ],
  "appomattox_virginia": [
    37.3570894,
    -78.8252911,
    "Appomattox, VA 24522, USA",
    0.75
  ],
  "coffee_alabama": [
    31.4751172,
    -86.0121573,
    "Coffee County, AL, USA",
    0.75
  ],
  "alabama_or_mississippi": [
    32.3182314,
    -86.902298,
    "Alabama, USA",
    0.75
  ],
  "jefferson_jefferson_county_tennessee": [
    36.0417825,
    -83.46435509999999,
    "Jefferson County, TN, USA",
    0.75
  ],
  "bibb_county_alabama": [
    32.9562798,
    -87.14228949999999,
    "Bibb County, AL, USA",
    0.75
  ],
  "pendleton_anderson_county_south_carolina": [
    34.6517733,
    -82.7837514,
    "Pendleton, SC, USA",
    0.75
  ],
  "birmingham_jefferson_county_alabama": [
    33.5185892,
    -86.8103567,
    "Birmingham, AL, USA",
    0.75
  ],
  "yorkville_pickens_county_alabama": [
    33.3339954,
    -88.0900762,
    "Pickens County, AL, USA",
    0.75
  ],
  "columbus_lowndes_county_mississippi": [
    33.4956744,
    -88.4272627,
    "Columbus, MS, USA",
    0.75
  ],
  "columbus_lowndes_county_mississippi_uusa": [
    33.4956744,
    -88.4272627,
    "Columbus, MS, USA",
    0.75
  ],
  "reform_pickens_county_alabama": [
    33.378451,
    -88.01530079999999,
    "Reform, AL, USA",
    0.75
  ],
  "reform_pickens_alabama": [
    33.378451,
    -88.01530079999999,
    "Reform, AL, USA",
    0.75
  ],
  "webster_county_mississippi": [
    33.5707456,
    -89.28472510000002,
    "Webster County, MS, USA",
    0.75
  ],
  "ethelville_alabama": [
    33.4156743,
    -88.21669910000001,
    "Ethelsville, AL 35461, USA",
    0.75
  ],
  "boston_township_williamson_county_tennessee": [
    35.8428441,
    -87.0325045,
    "Boston, TN 37179, USA",
    0.75
  ],
  "pickens_county_alabama": [
    33.3339954,
    -88.0900762,
    "Pickens County, AL, USA",
    0.75
  ],
  "new_hope_lowndes_county_mississippi": [
    33.446728,
    -88.32636029999999,
    "New Hope, MS 39702, USA",
    0.75
  ],
  "dallas_dallas_county_texas": [
    32.7766642,
    -96.79698789999999,
    "Dallas, TX, USA",
    0.75
  ],
  "abbeville_south_carolina": [
    34.1781719,
    -82.3790147,
    "Abbeville, SC 29620, USA",
    0.75
  ],
  "carrollton_pickens_alabama": [
    33.2617871,
    -88.0950263,
    "Carrollton, AL 35447, USA",
    0.75
  ],
  "warren_georgia_united_states": [
    33.4470392,
    -82.6915429,
    "Warren County, GA, USA",
    0.75
  ],
  "ethelsville_pickens_alabama_united_states": [
    33.4156743,
    -88.21669910000001,
    "Ethelsville, AL 35461, USA",
    0.75
  ],
  "indianapolis_indiana": [
    39.76909,
    -86.158018,
    "Indianapolis, IN, USA",
    0.75
  ],
  "massachusetts": [
    42.4072107,
    -71.3824374,
    "Massachusetts, USA",
    0.75
  ],
  "gulfport_harrison_mississippi": [
    30.3674198,
    -89.0928155,
    "Gulfport, MS, USA",
    0.75
  ],
  "oklahoma_city_oklahoma_united_states": [
    35.4688692,
    -97.519539,
    "Oklahoma City, OK, USA",
    0.75
  ],
  "dallas_texas": [
    32.7766642,
    -96.79698789999999,
    "Dallas, TX, USA",
    0.75
  ],
  "burleson_lee_co_texas": [
    32.5424289,
    -97.3230849,
    "Burleson, TX, USA",
    0.75
  ],
  "carolina_puerto_rico_united_states": [
    38.7945952,
    -106.5348379,
    "United States",
    0.75
  ],
  "lockhart_caldwell_texas_united_states": [
    29.8849441,
    -97.6699996,
    "Lockhart, TX 78644, USA",
    0.75
  ],
  "chamber_alabama_united_states": [
    33.2417826,
    -87.15805189999999,
    "Chambers, AL 35111, USA",
    0.75
  ],
  "brown_texas_united_states": [
    31.7705105,
    -98.92453429999999,
    "Brown County, TX, USA",
    0.75
  ],
  "u_cocle_panama": [
    8.400144899999999,
    -80.42152460000001,
    "Cocle, Cocl\u00e9 Province, Panama",
    0.75
  ],
  "pontatoc_mississippi": [
    34.2478831,
    -88.998673,
    "Pontotoc, MS 38863, USA",
    0.75
  ],
  "burelson_lee_texas": [
    32.5424289,
    -97.3230849,
    "Burleson, TX, USA",
    0.75
  ],
  "pontatoc_co_mississippi": [
    34.2478831,
    -88.998673,
    "Pontotoc, MS 38863, USA",
    0.75
  ],
  "merkel_taylor_texas": [
    32.4706777,
    -100.0128739,
    "Merkel, TX 79536, USA",
    0.75
  ],
  "lee_texas_united_states": [
    30.2967161,
    -96.9638624,
    "Lee County, TX, USA",
    0.75
  ],
  "lee_texas": [
    30.2967161,
    -96.9638624,
    "Lee County, TX, USA",
    0.75
  ],
  "pontotoc_mississippi": [
    34.2478831,
    -88.998673,
    "Pontotoc, MS 38863, USA",
    0.75
  ],
  "baird_callahan_texas": [
    32.3940168,
    -99.3942436,
    "Baird, TX, USA",
    0.75
  ],
  "hart_co_ky": [
    37.3101304,
    -85.84862360000001,
    "Hart County, KY, USA",
    0.75
  ],
  "red_river_texas": [
    32.76619675980588,
    -95.78772637584443,
    "Red River, United States",
    0.75
  ],
  "red_river_texas_united_states": [
    32.76619675980588,
    -95.78772637584443,
    "Red River, United States",
    0.75
  ],
  "austin_travis_texas": [
    30.267153,
    -97.7430608,
    "Austin, TX, USA",
    0.75
  ],
  "red_river_co_tx": [
    33.6072302,
    -94.976654,
    "Red River County, TX, USA",
    0.75
  ],
  "comanche_texas_united_states": [
    31.8973693,
    -98.60365809999999,
    "Comanche, TX 76442, USA",
    0.75
  ],
  "wichita_sedgwick_county_kansas": [
    37.693452,
    -97.3382202,
    "Wichita, KS, USA",
    0.75
  ],
  "caldwell_burleson_texas": [
    30.5313152,
    -96.69303029999999,
    "Caldwell, TX 77836, USA",
    0.75
  ],
  "mcfarland_california": [
    35.6780104,
    -119.2292748,
    "McFarland, CA 93250, USA",
    0.75
  ],
  "brunswick_glynn_georgia": [
    31.1510919,
    -81.4878157,
    "Brunswick, GA, USA",
    0.75
  ],
  "saint_louis_missouri": [
    38.6270025,
    -90.19940419999999,
    "St. Louis, MO, USA",
    0.75
  ],
  "new_orleans_louisiana": [
    29.9508941,
    -90.07583559999999,
    "New Orleans, LA, USA",
    0.75
  ],
  "east_saint_louis_saint_clair_illinois": [
    38.624514,
    -90.1506465,
    "East St Louis, IL, USA",
    0.75
  ],
  "houston_texas_united_states": [
    29.7600771,
    -95.37011079999999,
    "Houston, TX, USA",
    0.75
  ],
  "lowndes_county_mississippi": [
    33.473423,
    -88.4403883,
    "Lowndes County, MS, USA",
    0.75
  ],
  "white_arkansas_united_states": [
    33.0140144,
    -91.9956868,
    "White, AR 71635, USA",
    0.75
  ],
  "hawkins_tennessee": [
    36.4445545,
    -82.95015579999999,
    "Hawkins County, TN, USA",
    0.75
  ],
  "unknown_california": [
    36.778261,
    -119.4179324,
    "California, USA",
    0.75
  ],
  "lee_arkansas_united_states": [
    34.7712669,
    -90.8294002,
    "Lee County, AR, USA",
    0.75
  ],
  "hamilton_ohio": [
    39.39886790000001,
    -84.5587838,
    "Hamilton, OH, USA",
    0.75
  ],
  "boston_massachusetts": [
    42.3555076,
    -71.0565364,
    "Boston, MA, USA",
    0.75
  ],
  "west_armucky_walker_georgia": [
    34.6858231,
    -85.35496499999999,
    "Walker County, GA, USA",
    0.75
  ],
  "jasper_georgia": [
    34.4695524,
    -84.4289888,
    "Jasper, GA, USA",
    0.75
  ],
  "randolph_arkansas_united_states": [
    36.3457918,
    -90.9820668,
    "Randolph County, AR, USA",
    0.75
  ],
  "norfolk_independent_city_virginia": [
    36.8507689,
    -76.28587259999999,
    "Norfolk, VA, USA",
    0.75
  ],
  "lawrence_arkansas_united_states": [
    35.9969735,
    -91.13530200000001,
    "Lawrence County, AR, USA",
    0.75
  ],
  "pope_arkansas_united_states": [
    35.440627,
    -93.0175712,
    "Pope County, AR, USA",
    0.75
  ],
  "new_albany_floyd_indiana": [
    38.2856247,
    -85.8241312,
    "New Albany, IN 47150, USA",
    0.75
  ],
  "wayne_michigan": [
    42.2814269,
    -83.3863214,
    "Wayne, MI 48184, USA",
    0.75
  ],
  "cuyahoga_ohio": [
    41.7048247,
    -81.77870209999999,
    "Cuyahoga County, OH, USA",
    0.75
  ],
  "lavaca_texas": [
    29.33590539999999,
    -96.83509989999999,
    "Lavaca County, TX, USA",
    0.75
  ],
  "white_arkansas": [
    35.2900612,
    -91.7538817,
    "White County, AR, USA",
    0.75
  ],
  "reno_nevada": [
    39.529919,
    -119.8142691,
    "Reno, NV, USA",
    0.75
  ],
  "marengo_alabama": [
    32.2459085,
    -87.77633329999999,
    "Marengo County, AL, USA",
    0.75
  ],
  "reform_pickens_al": [
    33.378451,
    -88.01530079999999,
    "Reform, AL, USA",
    0.75
  ],
  "littlebury_essex_england": [
    52.032417,
    0.209853,
    "Littlebury, Saffron Walden CB11, UK",
    0.75
  ],
  "bertie_north_carolina": [
    36.0245185,
    -76.964306,
    "Bertie County, NC, USA",
    0.75
  ]
}